logscolor/__init__.py
logscolor/logscl.py
logscolor-1.5.dist-info/LICENSE
logscolor-1.5.dist-info/METADATA
logscolor-1.5.dist-info/WHEEL
logscolor-1.5.dist-info/top_level.txt
logscolor-1.5.dist-info/RECORD
