Metadata-Version: 2.1
Name: logscolor
Version: 1.5
Summary: Custom library for logging with colors, including execution date-time information and executable line (optional). Librería personalizada para logging con colores, con informacion de fecha - hora de ejecución y linea ejecutable (opcional)
Home-page: https://github.com/Pabl0VC/lib_logscolor
Author: Pablo Vega C
Author-email: pablovegac.93@gmail.com
Classifier: Programming Language :: Python :: 3
Classifier: License :: OSI Approved :: MIT License
Classifier: Operating System :: OS Independent
Requires-Python: >=3.6
License-File: LICENSE
Requires-Dist: colorama
